gpxviewer/__init__.py
gpxviewer/colorchooser.py
gpxviewer/configstore.py
gpxviewer/gpxdocument.py
gpxviewer/gpxmainwindow.py
gpxviewer/gpxmodel.py
gpxviewer/plotcanvas.py
gpxviewer/plotviewer.py
gpxviewer/pointconfigdialog.py
gpxviewer/rc_gpxviewer.py
gpxviewer/settingsdialog.py
gpxviewer/statwindow.py
gpxviewer/ui_mainwindow.py
gpxviewer/ui_plotwindow.py
gpxviewer/ui_pointconfigdialog.py
gpxviewer/ui_settingsdialog.py
gpxviewer/ui_statwindow.py
gpxviewer-3.1.2.data/data/share/applications/gpxviewer.desktop
gpxviewer-3.1.2.data/data/share/icons/hicolor/128x128/mimetypes/gpxviewer.png
gpxviewer-3.1.2.data/data/share/mime/packages/gpxviewer.xml
gpxviewer-3.1.2.data/data/share/pixmaps/gpxviewer.png
gpxviewer-3.1.2.dist-info/METADATA
gpxviewer-3.1.2.dist-info/WHEEL
gpxviewer-3.1.2.dist-info/entry_points.txt
gpxviewer-3.1.2.dist-info/top_level.txt
gpxviewer-3.1.2.dist-info/RECORD
